json_sort/__init__.py
json_sort/sorter.py
json_sorter-0.1.1.dist-info/METADATA
json_sorter-0.1.1.dist-info/WHEEL
json_sorter-0.1.1.dist-info/top_level.txt
json_sorter-0.1.1.dist-info/RECORD
