Metadata-Version: 2.1
Name: json-sorter
Version: 0.1.1
Summary: Simple package to Sort Json Content
Home-page: https://github.com/jasonfedorowich/jsonsort
Author: Jason
Author-email: jason.fedorowich@gmail.com
License: MIT
Platform: UNKNOWN
Requires-Python: >=3
